odoo/addons/extendable/README.rst
odoo/addons/extendable/__init__.py
odoo/addons/extendable/__manifest__.py
odoo/addons/extendable/registry.py
odoo/addons/extendable/models/__init__.py
odoo/addons/extendable/models/extendable_registry_loader.py
odoo/addons/extendable/models/ir_http.py
odoo/addons/extendable/readme/CONTRIBUTORS.rst
odoo/addons/extendable/readme/DESCRIPTION.rst
odoo/addons/extendable/readme/ROADMAP.rst
odoo/addons/extendable/readme/USAGE.rst
odoo/addons/extendable/static/description/icon.png
odoo/addons/extendable/static/description/index.html
odoo/addons/extendable/tests/__init__.py
odoo/addons/extendable/tests/common.py
odoo13_addon_extendable-13.0.1.0.0.dist-info/METADATA
odoo13_addon_extendable-13.0.1.0.0.dist-info/WHEEL
odoo13_addon_extendable-13.0.1.0.0.dist-info/top_level.txt
odoo13_addon_extendable-13.0.1.0.0.dist-info/RECORD
